{
  "pseudo": "q",
  "tour": false,
  "tuiles": [
    {"valeur":7,"couleur":"O","joker":false},
    {"valeur":9,"couleur":"R","joker":false},
    {"valeur":9,"couleur":"B","joker":false},
    {"valeur":4,"couleur":"V","joker":false},
    {"valeur":1,"couleur":"B","joker":false},
    {"valeur":1,"couleur":"O","joker":false},
    {"valeur":6,"couleur":"R","joker":false},
    {"valeur":0,"couleur":"J","joker":true},
    {"valeur":8,"couleur":"O","joker":false},
    {"valeur":7,"couleur":"O","joker":false},
    {"valeur":12,"couleur":"R","joker":false},
    {"valeur":2,"couleur":"O","joker":false},
    {"valeur":9,"couleur":"O","joker":false},
    {"valeur":6,"couleur":"O","joker":false}
  ]
}
